{
  "id": "famed-ignis-160",
  "name": {
    "en": "Lampe opératoire IGNIS 160",
    "fr": "Lampe opératoire IGNIS 160"
  },
  "brand": {
    "name": "FAMED",
    "description": ""
  },
  "category": {
    "canonical": "surgery",
    "display": {
      "en": "eclairage-operatoire",
      "fr": "Éclairage opératoire"
    }
  },
  "short_description": {
    "en": "Lampe opératoire LED haut de gamme avec coupole simple ou double offrant un éclairage chirurgical précis.",
    "fr": "Lampe opératoire LED haut de gamme avec coupole simple ou double, offrant un éclairage optimal pour interventions chirurgicales complexes."
  },
  "full_description": {
    "en": "La lampe opératoire IGNIS 160 est conçue pour fournir un éclairage chirurgical de haute précision. Disponible en version simple ou double coupole, elle assure une excellente visibilité et un confort visuel maximal. Son intensité lumineuse réglable et son rendu des couleurs précis permettent une précision accrue lors des interventions médicales et chirurgicales.",
    "fr": "La lampe opératoire IGNIS 160 est conçue pour fournir un éclairage chirurgical de haute précision.  \nDisponible en version simple ou double coupole, elle assure une excellente visibilité et un confort visuel maximal.  \nSon intensité lumineuse réglable et son rendu des couleurs précis permettent une précision accrue lors des procédures médicales et chirurgicales.\n"
  },
  "availability": "in_stock",
  "images": [
    "../../assets/products/surgery/lights/famed-ignis-160/ignis-160-1.webp",
    "../../assets/products/surgery/lights/famed-ignis-160/ignis-160-2.webp",
    "../../assets/products/surgery/lights/famed-ignis-160/ignis-160-3.webp",
    "../../assets/products/surgery/lights/famed-ignis-160/ignis-160-4.webp"
  ],
  "attributes": [
    {
      "canonical_name": "alimentation",
      "display_label": {
        "fr": "Tension d’alimentation"
      },
      "category": "Electrical",
      "type": "string",
      "value": "24 V DC"
    },
    {
      "canonical_name": "intensite_lumineuse",
      "display_label": {
        "fr": "Intensité lumineuse à 1 m"
      },
      "category": "Lighting",
      "type": "number",
      "value": {
        "qty": 160000,
        "unit": "lux"
      }
    },
    {
      "canonical_name": "variation_intensite",
      "display_label": {
        "fr": "Variation de l’intensité lumineuse"
      },
      "category": "Lighting",
      "type": "range",
      "value": {
        "min": 25,
        "max": 100,
        "unit": "%"
      }
    },
    {
      "canonical_name": "indice_rendu_couleurs",
      "display_label": {
        "fr": "Indice de rendu des couleurs (Ra)"
      },
      "category": "Lighting",
      "type": "number",
      "value": 96
    },
    {
      "canonical_name": "temperature_couleur",
      "display_label": {
        "fr": "Température de couleur"
      },
      "category": "Lighting",
      "type": "enum",
      "value": {
        "values": [4000, 4400, 4800],
        "unit": "K"
      }
    },
    {
      "canonical_name": "diametre_champ_d10",
      "display_label": {
        "fr": "Diamètre du champ opératoire (d10)"
      },
      "category": "Lighting",
      "type": "number",
      "value": {
        "qty": 240,
        "unit": "mm"
      }
    },
    {
      "canonical_name": "diametre_spot_d50",
      "display_label": {
        "fr": "Diamètre du spot lumineux (d50)"
      },
      "category": "Lighting",
      "type": "number",
      "value": {
        "qty": 120,
        "unit": "mm"
      }
    },
    {
      "canonical_name": "champ_reglable",
      "display_label": {
        "fr": "Diamètre du champ opératoire réglable"
      },
      "category": "Lighting",
      "type": "boolean",
      "value": true
    },
    {
      "canonical_name": "profondeur_eclairage_l1_l2_20",
      "display_label": {
        "fr": "Profondeur d’éclairage L1+L2 (20 %)"
      },
      "category": "Lighting",
      "type": "number",
      "value": {
        "qty": 140,
        "unit": "cm"
      }
    },
    {
      "canonical_name": "profondeur_eclairage_l1_l2_60",
      "display_label": {
        "fr": "Profondeur d’éclairage L1+L2 (60 %)"
      },
      "category": "Lighting",
      "type": "number",
      "value": {
        "qty": 85,
        "unit": "cm"
      }
    },
    {
      "canonical_name": "elevation_temperature",
      "display_label": {
        "fr": "Élévation de température au niveau de la tête du chirurgien"
      },
      "category": "Safety",
      "type": "string",
      "value": "< 1 °C"
    },
    {
      "canonical_name": "consommation",
      "display_label": {
        "fr": "Consommation électrique de la coupole"
      },
      "category": "Electrical",
      "type": "number",
      "value": {
        "qty": 80,
        "unit": "W"
      }
    },
    {
      "canonical_name": "classe_isolation",
      "display_label": {
        "fr": "Classe d’isolation"
      },
      "category": "Electrical",
      "type": "string",
      "value": "Classe I"
    },
    {
      "canonical_name": "indice_protection",
      "display_label": {
        "fr": "Indice de protection"
      },
      "category": "Mechanical",
      "type": "string",
      "value": "IP54"
    }
  ],
  "compliance": {
    "certifications": [
      "CE",
      "Règlement (UE) 2017/745 (MDR)"
    ],
    "standards": [
      "IEC 60601-1:2011",
      "IEC 60601-2-41:2022",
      "IEC 60601-1-2:2015"
    ]
  },
  "documents": {
    "official_page": "https://famed.pl/en/products/surgical-lights/ignis-160/",
    "specs": "https://famed.pl/media/wlzagfgt/10-09-2021-karta-produktowa-ignis-en-1.pdf"
  }
}
